Metadata-Version: 2.4
Name: mcp-task-orchestrator
Version: 1.8.0
Summary: A Model Context Protocol server for task orchestration
Home-page: https://github.com/EchoingVesper/mcp-task-orchestrator
Author: Echoing Vesper
Author-email: noreply@github.com
Project-URL: Homepage, https://github.com/EchoingVesper/mcp-task-orchestrator
Project-URL: Documentation, https://github.com/EchoingVesper/mcp-task-orchestrator/blob/main/README.md
Project-URL: Issues, https://github.com/EchoingVesper/mcp-task-orchestrator/issues
Project-URL: Releases, https://github.com/EchoingVesper/mcp-task-orchestrator/releases
Project-URL: Repository, https://github.com/EchoingVesper/mcp-task-orchestrator
Keywords: mcp,ai,task-orchestration,claude,automation,llm,workflow
Classifier: Development Status :: 4 - Beta
Classifier: Intended Audience :: Developers
Classifier: License :: OSI Approved :: MIT License
Classifier: Programming Language :: Python :: 3
Classifier: Programming Language :: Python :: 3.8
Classifier: Programming Language :: Python :: 3.9
Classifier: Programming Language :: Python :: 3.10
Classifier: Programming Language :: Python :: 3.11
Classifier: Topic :: Software Development :: Libraries :: Python Modules
Classifier: Topic :: Scientific/Engineering :: Artificial Intelligence
Classifier: Environment :: Console
Classifier: Operating System :: OS Independent
Requires-Python: >=3.8
License-File: LICENSE
Requires-Dist: mcp>=1.9.0
Requires-Dist: pydantic>=2.0.0
Requires-Dist: jinja2>=3.1.0
Requires-Dist: pyyaml>=6.0.0
Requires-Dist: aiofiles>=23.0.0
Requires-Dist: psutil>=5.9.0
Requires-Dist: filelock>=3.12.0
Requires-Dist: sqlalchemy>=2.0.0
Requires-Dist: alembic>=1.10.0
Requires-Dist: typer>=0.9.0
Requires-Dist: rich>=13.0.0
Provides-Extra: dev
Requires-Dist: pytest>=7.0.0; extra == "dev"
Requires-Dist: pytest-asyncio>=0.21.0; extra == "dev"
Provides-Extra: cli
Requires-Dist: typer>=0.9.0; extra == "cli"
Requires-Dist: rich>=13.0.0; extra == "cli"
Dynamic: author
Dynamic: author-email
Dynamic: classifier
Dynamic: description
Dynamic: description-content-type
Dynamic: home-page
Dynamic: keywords
Dynamic: license-file
Dynamic: project-url
Dynamic: provides-extra
Dynamic: requires-dist
Dynamic: requires-python
Dynamic: summary
